AUTHORS.rst
CONTRIBUTING.rst
HISTORY.rst
MANIFEST.in
README.rst
setup.cfg
setup.py
Quadranpy/Quadranpy.py
Quadranpy/__init__.py
Quadranpy.egg-info/PKG-INFO
Quadranpy.egg-info/SOURCES.txt
Quadranpy.egg-info/dependency_links.txt
Quadranpy.egg-info/not-zip-safe
Quadranpy.egg-info/top_level.txt
docs/Makefile
docs/authors.rst
docs/conf.py
docs/contributing.rst
docs/history.rst
docs/index.rst
docs/installation.rst
docs/make.bat
docs/readme.rst
docs/usage.rst
tests/__init__.py
tests/test_Quadranpy.py