Metadata-Version: 1.2
Name: Quadranpy
Version: 0.1.0
Summary: QuadraNpy process Sales and Payment reports
Home-page: https://github.com/hmelino/Quadranpy
Author: Matus Hmelar
Author-email: mhmelar@gmail.com
License: UNKNOWN
Keywords: Quadranpy
Platform: UNKNOWN
Classifier: Development Status :: 2 - Pre-Alpha
Classifier: Intended Audience :: Developers
Classifier: Natural Language :: English
Classifier: Programming Language :: Python :: 3
Classifier: Programming Language :: Python :: 3.5
Classifier: Programming Language :: Python :: 3.6
Classifier: Programming Language :: Python :: 3.7
Classifier: Programming Language :: Python :: 3.8
Requires-Python: >=3.5
